azolla/__init__.py
azolla/_version.py
azolla/cli.py
azolla/client.py
azolla/exceptions.py
azolla/py.typed
azolla/retry.py
azolla/task.py
azolla/types.py
azolla/worker.py
azolla/_grpc/__init__.py
azolla/_grpc/common_pb2.py
azolla/_grpc/common_pb2.pyi
azolla/_grpc/common_pb2_grpc.py
azolla/_grpc/orchestrator_pb2.py
azolla/_grpc/orchestrator_pb2.pyi
azolla/_grpc/orchestrator_pb2_grpc.py
azolla/_internal/__init__.py
azolla/_internal/utils.py
azolla-0.1.0.dist-info/METADATA
azolla-0.1.0.dist-info/WHEEL
azolla-0.1.0.dist-info/entry_points.txt
azolla-0.1.0.dist-info/licenses/LICENSE
azolla-0.1.0.dist-info/RECORD
