Metadata-Version: 2.4
Name: azolla
Version: 0.1.0
Summary: Python client library for Azolla distributed task processing
Project-URL: Homepage, https://github.com/azolla-io/azolla
Project-URL: Documentation, https://docs.azolla.io/python-client
Project-URL: Repository, https://github.com/azolla-io/azolla.git
Project-URL: Bug Tracker, https://github.com/azolla-io/azolla/issues
Project-URL: Changelog, https://github.com/azolla-io/azolla/blob/main/clients/python/CHANGELOG.md
Author-email: Azolla Team <team@azolla.io>
Maintainer-email: Azolla Team <team@azolla.io>
License: Apache-2.0
License-File: LICENSE
Keywords: async,distributed,queue,tasks,worker
Classifier: Development Status :: 4 - Beta
Classifier: Intended Audience :: Developers
Classifier: License :: OSI Approved :: Apache Software License
Classifier: Operating System :: OS Independent
Classifier: Programming Language :: Python :: 3
Classifier: Programming Language :: Python :: 3.9
Classifier: Programming Language :: Python :: 3.10
Classifier: Programming Language :: Python :: 3.11
Classifier: Programming Language :: Python :: 3.12
Classifier: Programming Language :: Python :: 3.13
Classifier: Topic :: Software Development :: Libraries :: Python Modules
Classifier: Topic :: System :: Distributed Computing
Classifier: Typing :: Typed
Requires-Python: >=3.9
Requires-Dist: grpcio-status>=1.50.0
Requires-Dist: grpcio>=1.50.0
Requires-Dist: pydantic<3.0.0,>=2.0.0
Requires-Dist: typing-extensions>=4.5.0; python_version < '3.11'
Provides-Extra: all
Requires-Dist: black>=24.0.0; extra == 'all'
Requires-Dist: factory-boy>=3.3.0; extra == 'all'
Requires-Dist: freezegun>=1.2.0; extra == 'all'
Requires-Dist: httpx>=0.24.0; extra == 'all'
Requires-Dist: mypy>=1.9.0; extra == 'all'
Requires-Dist: opentelemetry-api>=1.20.0; extra == 'all'
Requires-Dist: orjson>=3.8.0; extra == 'all'
Requires-Dist: pre-commit>=4.0.0; extra == 'all'
Requires-Dist: prometheus-client>=0.17.0; extra == 'all'
Requires-Dist: psutil>=5.9.0; extra == 'all'
Requires-Dist: pytest-asyncio>=0.21.0; extra == 'all'
Requires-Dist: pytest-cov>=4.0.0; extra == 'all'
Requires-Dist: pytest-mock>=3.11.0; extra == 'all'
Requires-Dist: pytest>=7.0.0; extra == 'all'
Requires-Dist: ruff>=0.8.0; extra == 'all'
Requires-Dist: sphinx-autodoc-typehints>=1.24.0; extra == 'all'
Requires-Dist: sphinx-rtd-theme>=1.3.0; extra == 'all'
Requires-Dist: sphinx>=7.0.0; extra == 'all'
Requires-Dist: structlog>=23.0.0; extra == 'all'
Requires-Dist: uvloop>=0.17.0; (sys_platform != 'win32') and extra == 'all'
Provides-Extra: dev
Requires-Dist: black>=24.0.0; extra == 'dev'
Requires-Dist: mypy>=1.9.0; extra == 'dev'
Requires-Dist: pre-commit>=4.0.0; extra == 'dev'
Requires-Dist: pytest-asyncio>=0.21.0; extra == 'dev'
Requires-Dist: pytest-cov>=4.0.0; extra == 'dev'
Requires-Dist: pytest>=7.0.0; extra == 'dev'
Requires-Dist: ruff>=0.8.0; extra == 'dev'
Provides-Extra: docs
Requires-Dist: sphinx-autodoc-typehints>=1.24.0; extra == 'docs'
Requires-Dist: sphinx-rtd-theme>=1.3.0; extra == 'docs'
Requires-Dist: sphinx>=7.0.0; extra == 'docs'
Provides-Extra: integration
Requires-Dist: httpx>=0.24.0; extra == 'integration'
Requires-Dist: psutil>=5.9.0; extra == 'integration'
Provides-Extra: monitoring
Requires-Dist: opentelemetry-api>=1.20.0; extra == 'monitoring'
Requires-Dist: prometheus-client>=0.17.0; extra == 'monitoring'
Requires-Dist: structlog>=23.0.0; extra == 'monitoring'
Provides-Extra: performance
Requires-Dist: orjson>=3.8.0; extra == 'performance'
Requires-Dist: uvloop>=0.17.0; (sys_platform != 'win32') and extra == 'performance'
Provides-Extra: testing
Requires-Dist: factory-boy>=3.3.0; extra == 'testing'
Requires-Dist: freezegun>=1.2.0; extra == 'testing'
Requires-Dist: pytest-mock>=3.11.0; extra == 'testing'
